metannvis/Main.py
metannvis/__init__.py
metannvis/frameworks/Framework.py
metannvis/frameworks/PyTorchFramework.py
metannvis/frameworks/TensorFlow2Framework.py
metannvis/frameworks/__init__.py
metannvis/frameworks/framework_keys.py
metannvis/methods/AbstractAttributionMethod.py
metannvis/methods/AbstractFeatureVisualizationMethod.py
metannvis/methods/AbstractMethod.py
metannvis/methods/CaptumDeconvolution.py
metannvis/methods/CaptumDeepLift.py
metannvis/methods/CaptumFeatureAblation.py
metannvis/methods/CaptumFeaturePermutation.py
metannvis/methods/CaptumGradCAM.py
metannvis/methods/CaptumGradientSHAP.py
metannvis/methods/CaptumInputXGradient.py
metannvis/methods/CaptumIntegratedGradients.py
metannvis/methods/CaptumLayerActivation.py
metannvis/methods/CaptumLayerConductance.py
metannvis/methods/CaptumLayerDeepLift.py
metannvis/methods/CaptumLayerFeatureAblation.py
metannvis/methods/CaptumLayerGradientSHAP.py
metannvis/methods/CaptumLayerGradientXActivation.py
metannvis/methods/CaptumLayerIntegratedGradients.py
metannvis/methods/CaptumNeuronConductance.py
metannvis/methods/CaptumNeuronDeconvolution.py
metannvis/methods/CaptumNeuronDeepLift.py
metannvis/methods/CaptumNeuronFeatureAblation.py
metannvis/methods/CaptumNeuronGradient.py
metannvis/methods/CaptumNeuronGradientSHAP.py
metannvis/methods/CaptumNeuronIntegratedGradients.py
metannvis/methods/CaptumSaliency.py
metannvis/methods/TfKerasVisActivationMaximization.py
metannvis/methods/TfKerasVisGradcam.py
metannvis/methods/TfKerasVisLayerCAM.py
metannvis/methods/TfKerasVisSaliency.py
metannvis/methods/TfKerasVisScoreCAM.py
metannvis/methods/TfKervasVisGradcamPlusPlus.py
metannvis/methods/__init__.py
metannvis/methods/method_keys.py
metannvis/toolsets/Captum.py
metannvis/toolsets/TfKerasVis.py
metannvis/toolsets/Toolset.py
metannvis/toolsets/__init__.py
metannvis/toolsets/toolset_keys.py
metannvis/translations/Tf2TorchTranslation.py
metannvis/translations/Torch2TfTranslation.py
metannvis/translations/Translation.py
metannvis-0.0.3.dist-info/METADATA
metannvis-0.0.3.dist-info/WHEEL
metannvis-0.0.3.dist-info/licenses/LICENSE
metannvis-0.0.3.dist-info/RECORD
