Metadata-Version: 2.1
Name: metaNNvis
Version: 0.0.3
Summary: A meta-tool for cross-framework access to PyTorch and Tensorflow visualisation methods
Project-URL: Homepage, https://github.com/sfluegel05/metaNNvis
Project-URL: Bug Tracker, https://github.com/sfluegel05/metaNNvis/issues
Author-email: Simon Flügel <sfluegel@ovgu.de>
License: MIT License
License-File: LICENSE
Classifier: License :: OSI Approved :: MIT License
Classifier: Operating System :: OS Independent
Classifier: Programming Language :: Python :: 3
Requires-Python: >=3.7
